vre_repository_connector/__init__.py
vre_repository_connector/api/__init__.py
vre_repository_connector/api/base.py
vre_repository_connector/api/dbrepo.py
vre_repository_connector/api/inveniordm.py
vre_repository_connector/auto.py
vre_repository_connector/cli.py
vre_repository_connector/utils.py
vre_repository_connector-0.3.3.dist-info/LICENSE
vre_repository_connector-0.3.3.dist-info/METADATA
vre_repository_connector-0.3.3.dist-info/WHEEL
vre_repository_connector-0.3.3.dist-info/entry_points.txt
vre_repository_connector-0.3.3.dist-info/RECORD
