Metadata-Version: 2.3
Name: VRE-Repository-Connector
Version: 0.3.3
Summary: Library for connecting the virtual research environment of TU Wien with its research data repositories
License: MIT
Author: Maximilian Moser
Author-email: maximilian.moser@tuwien.ac.at
Requires-Python: >=3.11
Classifier: License :: OSI Approved :: MIT License
Classifier: Programming Language :: Python :: 3
Classifier: Programming Language :: Python :: 3.11
Classifier: Programming Language :: Python :: 3.12
Classifier: Programming Language :: Python :: 3.13
Requires-Dist: click (>=8.1.8,<9.0.0)
Requires-Dist: dbrepo (>=1.4.4rc1,<2.0.0)
Requires-Dist: inveniordm-py (>=0.1.0,<0.2.0)
Requires-Dist: pandas (>=2,<3)
Project-URL: Repository, https://gitlab.tuwien.ac.at/fairdata/vre-repository-connector
